
#### 描述

```python
a = 0
l = [0, 1, 2]

c, a = l[a], a + 1
print (c, a)

a, c = a + 1, l[a]
print (c, a)
```

#### 要求
请写出打印内容


<details>
<summary>详解</summary>

答案

```python
In [1]: a = 0

In [2]: l = [0, 1, 2]

In [3]: c, a = l[a], a + 1

In [4]: print (c, a)
0 1

In [5]: a, c = a + 1, l[a]

In [6]: print (c, a)
1 2
```

原理

```python
In [1]: a = 0

In [2]: l = [0, 1, 2]

In [3]: c, a = l[a], a + 1

In [4]: print (c, a)
0 1

In [5]: import dis

In [6]: dis.dis('a, c = a + 1, l[a]')
# TOS : 栈顶
# TOS1: 栈顶之下一个

              0 LOAD_NAME                0 (a)
              # a入栈             栈: [1]
              
              2 LOAD_CONST               0 (1)
              # 1入栈             栈: [1, 1]
              
              4 BINARY_ADD
              # TOS = TOS1 + TOS  栈: [2]
              
              6 LOAD_NAME                1 (l)
              # l入栈             栈: [l, 2]
              
              8 LOAD_NAME                0 (a)
              # a入栈             栈: [1, l, 2]
              
             10 BINARY_SUBSCR
              # TOS = TOS1[TOS]   栈: [1, 2]
              # 栈顶 = l[1] = 1
             
             12 ROT_TWO
              # 交换TOS, TOS1      栈: [2, 1]
             
             14 STORE_NAME               0 (a)
              # a = 2              栈: [1]
             
             16 STORE_NAME               2 (c)
              # c = 1              栈: [2, l[1]]
             
             18 LOAD_CONST               1 (None)
             20 RETURN_VALUE
```

</details>


<font size=1.5>Author: [twfb](https://github.com/dhgdhg)</font> 
